{
	"$schema": "https://raw.githubusercontent.com/shiptest-ss13/Shiptest/master/_maps/ship_config_schema.json",
	"map_name": "Vagrant-class Hunting Vessel",
	"faction": "/datum/faction/srm",
	"prefix": "SRSV",
	"namelists": [
		"SAINT-ROUMAIN",
		"BEASTS"
	],
	"map_short_name": "Vagrant-class",
	"map_path": "_maps/shuttles/roumain/srm_vagrant.dmm",
	"description": "One of the smallest vessels available to Montagnes of the Saint-Roumaine-Militia, the Vagrant-Class provides hunters with an affordable, swift journey to their hunting grounds. This vessel features a rocky terrarium prepared with a seed bank perfectly fit for producing trickwines. Hunters and apprenticing shadows alike can find comfort around a campfire, utilizing a strong armory and potent brews to push them through their trials in service to the huntsman.",
	"tags": [
		"Botany",
		"Combat",
		"Specialist"
	],
	"map_id": "srm_vagrant",
	"limit": 1,
	"job_slots": {
		"Hunter Montagne": {
			"outfit": "/datum/outfit/job/roumain/captain",
			"officer": true,
			"slots": 1
		},
		"Hunter Colligne": {
			"outfit": "/datum/outfit/job/roumain/hop",
			"officer": true,
			"slots": 1
		},
		"Flamebearer": {
			"outfit": "/datum/outfit/job/roumain/flamebearer",
			"slots": 1
		},
		"Hunter": {
			"outfit": "/datum/outfit/job/roumain/security",
			"slots": 1
		},
		"Shadow": {
			"outfit": "/datum/outfit/job/roumain/assistant",
			"slots": 1
		}
	},
	"enabled": true
}
